openai_assistant/__init__.py
openai_assistant/assistant_manager.py
openai_assistant/file_manager.py
openai_assistant/openai_assistant.py
openai_assistant/thread_manager.py
openai_assistant/tool_functions_map.py
openai_assistant/utils.py
openai_assistant/vector_stores_manager.py
openai_assistant-0.1.8.dist-info/LICENSE
openai_assistant-0.1.8.dist-info/METADATA
openai_assistant-0.1.8.dist-info/WHEEL
openai_assistant-0.1.8.dist-info/top_level.txt
openai_assistant-0.1.8.dist-info/RECORD
