Metadata-Version: 2.1
Name: openai_assistant
Version: 0.1.8
Summary: An asynchronous Python package for integrating OpenAI assistant.
Home-page: 
Author: Xiaobocute
Author-email: Business@xiaobo.tw
License: MIT
License-File: LICENSE
